dataproc_jupyter_plugin/__init__.py
dataproc_jupyter_plugin/_version.py
dataproc_jupyter_plugin/credentials.py
dataproc_jupyter_plugin/handlers.py
dataproc_jupyter_plugin/urls.py
dataproc_jupyter_plugin/commons/commands.py
dataproc_jupyter_plugin/commons/constants.py
dataproc_jupyter_plugin/controllers/bigquery.py
dataproc_jupyter_plugin/controllers/checkApiEnabled.py
dataproc_jupyter_plugin/controllers/version.py
dataproc_jupyter_plugin/services/bigquery.py
dataproc_jupyter_plugin/services/version.py
dataproc_jupyter_plugin/tests/__init__.py
dataproc_jupyter_plugin/tests/mocks.py
dataproc_jupyter_plugin/tests/test_bigquery.py
dataproc_jupyter_plugin/tests/test_checkApiEnabled.py
dataproc_jupyter_plugin/tests/test_credentials.py
dataproc_jupyter_plugin/tests/test_handlers.py
dataproc_jupyter_plugin-0.1.94.data/data/etc/jupyter/jupyter_notebook_config.d/dataproc_jupyter_plugin.json
dataproc_jupyter_plugin-0.1.94.data/data/etc/jupyter/jupyter_server_config.d/dataproc_jupyter_plugin.json
dataproc_jupyter_plugin-0.1.94.data/data/share/jupyter/labextensions/dataproc_jupyter_plugin/build_log.json
dataproc_jupyter_plugin-0.1.94.data/data/share/jupyter/labextensions/dataproc_jupyter_plugin/package.json
dataproc_jupyter_plugin-0.1.94.data/data/share/jupyter/labextensions/dataproc_jupyter_plugin/schemas/dataproc_jupyter_plugin/package.json.orig
dataproc_jupyter_plugin-0.1.94.data/data/share/jupyter/labextensions/dataproc_jupyter_plugin/schemas/dataproc_jupyter_plugin/plugin.json
dataproc_jupyter_plugin-0.1.94.data/data/share/jupyter/labextensions/dataproc_jupyter_plugin/static/lib_index_js.8651b97acbd14da37148.js
dataproc_jupyter_plugin-0.1.94.data/data/share/jupyter/labextensions/dataproc_jupyter_plugin/static/lib_index_js.8651b97acbd14da37148.js.map
dataproc_jupyter_plugin-0.1.94.data/data/share/jupyter/labextensions/dataproc_jupyter_plugin/static/node_modules_babel_runtime_helpers_esm_extends_js-node_modules_emotion_memoize_dist_emotion-m-344ccf.67974ccedf550497bbba.js
dataproc_jupyter_plugin-0.1.94.dist-info/METADATA
dataproc_jupyter_plugin-0.1.94.dist-info/WHEEL
dataproc_jupyter_plugin-0.1.94.dist-info/licenses/LICENSE
dataproc_jupyter_plugin-0.1.94.dist-info/RECORD
