Metadata-Version: 2.4
Name: dataproc_jupyter_plugin
Version: 0.1.94
Dynamic: Keywords
Summary: It is a plugin to work with dataproc services in Jupyterlab
Project-URL: Homepage, https://github.com/GoogleCloudDataproc/dataproc-jupyter-plugin
Project-URL: Bug Tracker, https://github.com/GoogleCloudDataproc/dataproc-jupyter-plugin/issues
Project-URL: Repository, https://github.com/GoogleCloudDataproc/dataproc-jupyter-plugin.git
Author-email: google <dataproc-plugins@google.com>
License:                                  Apache License
License-File: LICENSE
Classifier: Framework :: Jupyter
Classifier: Framework :: Jupyter :: JupyterLab
Classifier: Framework :: Jupyter :: JupyterLab :: 4
Classifier: Framework :: Jupyter :: JupyterLab :: Extensions
Classifier: Framework :: Jupyter :: JupyterLab :: Extensions :: Prebuilt
Classifier: License :: OSI Approved :: BSD License
Classifier: Programming Language :: Python
Classifier: Programming Language :: Python :: 3
Classifier: Programming Language :: Python :: 3.8
Classifier: Programming Language :: Python :: 3.9
Classifier: Programming Language :: Python :: 3.10
Classifier: Programming Language :: Python :: 3.11
Requires-Python: >=3.8
Requires-Dist: aiofiles<23,>=22.1.0
Requires-Dist: aiohttp~=3.9.5
Requires-Dist: cachetools>=4.2.4
Requires-Dist: google-cloud-jupyter-config>=0.0.10
Requires-Dist: google-cloud-storage~=2.18.2
Requires-Dist: jupyter-server<3,>=2.7.3
Requires-Dist: kernels-mixer>=0.0.13
Requires-Dist: pendulum>=3.0.0
Requires-Dist: pydantic~=1.10.0
Requires-Dist: scheduler-jupyter-plugin>=0.1.0
Provides-Extra: test
Requires-Dist: coverage; extra == 'test'
Requires-Dist: pytest; extra == 'test'
Requires-Dist: pytest-asyncio; extra == 'test'
Requires-Dist: pytest-cov; extra == 'test'
Requires-Dist: pytest-jupyter[server]>=0.6.0; extra == 'test'
